al360_taiutils/__init__.py
al360_taiutils/exceptions.py
al360_taiutils/version.py
al360_taiutils/cohort/__init__.py
al360_taiutils/cohort/cohort.py
al360_taiutils/cohort/constants.py
al360_taiutils/common/__init__.py
al360_taiutils/common/retries.py
al360_taiutils/data_processing/__init__.py
al360_taiutils/data_processing/data_processing_utils.py
al360_taiutils/dataset/__init__.py
al360_taiutils/dataset/dataset.py
al360_taiutils/models/__init__.py
al360_taiutils/models/model_utils.py
al360_taiutils/sampling/__init__.py
al360_taiutils/sampling/random_sampling.py
al360_taiutils/webservice/__init__.py
al360_taiutils/webservice/webservice.py
al360_taiutils-0.4.2.dist-info/LICENSE
al360_taiutils-0.4.2.dist-info/METADATA
al360_taiutils-0.4.2.dist-info/WHEEL
al360_taiutils-0.4.2.dist-info/top_level.txt
al360_taiutils-0.4.2.dist-info/RECORD
