Metadata-Version: 2.1
Name: al360_taiutils
Version: 0.4.2
Summary: Common basic utilities used across various RAI tools
Home-page: https://github.com/affectlog360/al360-trustworthy-ai-widgets
Author: Roman Lutz, Ilya Matiach, Ke Xu
Author-email: al360_taiwidgets-maintain@affectlog.com
Classifier: Programming Language :: Python :: 3.7
Classifier: Programming Language :: Python :: 3.8
Classifier: Programming Language :: Python :: 3.9
Classifier: Programming Language :: Python :: 3.10
Classifier: Programming Language :: Python :: 3.11
Classifier: License :: OSI Approved :: MIT License
Classifier: Operating System :: OS Independent
Classifier: Development Status :: 3 - Alpha
Requires-Python: >=3.7
License-File: LICENSE
Requires-Dist: numpy
Requires-Dist: pandas
Requires-Dist: requests
Requires-Dist: scikit-learn
Requires-Dist: scipy
